{
    "fluentMethods": true,
    "clientRootFolder": "",
    "relationships": [
        {
            "relationshipName": "store",
            "otherEntityName": "store",
            "relationshipType": "many-to-one",
            "relationshipValidateRules": [
                "required"
            ],
            "otherEntityField": "name"
        },
        {
            "relationshipName": "item",
            "otherEntityName": "item",
            "relationshipType": "many-to-one",
            "relationshipValidateRules": [
                "required"
            ],
            "otherEntityField": "name"
        }
    ],
    "fields": [
        {
            "fieldName": "price",
            "fieldType": "Integer",
            "fieldValidateRules": [
                "required"
            ]
        },
        {
            "fieldName": "favoriteInd",
            "fieldType": "Boolean"
        }
    ],
    "changelogDate": "20180727030630",
    "dto": "no",
    "searchEngine": false,
    "service": "serviceImpl",
    "entityTableName": "store_grocery_item",
    "jpaMetamodelFiltering": false,
    "pagination": "no"
}
